expectly/__init__.py
expectly/_expect.py
expectly-0.1.8.dist-info/DESCRIPTION.rst
expectly-0.1.8.dist-info/METADATA
expectly-0.1.8.dist-info/RECORD
expectly-0.1.8.dist-info/WHEEL
expectly-0.1.8.dist-info/metadata.json
expectly-0.1.8.dist-info/top_level.txt
