Metadata-Version: 2.0
Name: expectly
Version: 0.1.8
Summary: An HTTP API centric BDD style test framework
Home-page: https://github.com/huntcsg/expectly
Author: Hunter Senft-Grupp
Author-email: huntcsg@gmail.com
License: UNKNOWN
Keywords: testing bdd rest api expect rspec chakram chai
Platform: UNKNOWN
Classifier: Development Status :: 2 - Pre-Alpha
Classifier: Intended Audience :: Developers
Classifier: License :: OSI Approved :: MIT License
Classifier: Natural Language :: English
Classifier: Programming Language :: Python :: 3
Classifier: Programming Language :: Python :: 3.6
Classifier: Programming Language :: Python :: Implementation :: CPython
Classifier: Topic :: Software Development :: Libraries
Requires-Dist: jsonschema
Requires-Dist: jmespath
Provides-Extra: dev
Requires-Dist: pytest; extra == 'dev'
Requires-Dist: pytest-cov; extra == 'dev'
Requires-Dist: pytest-html; extra == 'dev'
Requires-Dist: requests; extra == 'dev'
Requires-Dist: requests-mock; extra == 'dev'
Requires-Dist: sphinx; extra == 'dev'
Requires-Dist: sphinx-rtd-theme; extra == 'dev'
Requires-Dist: isort; extra == 'dev'
Requires-Dist: flake8; extra == 'dev'
Requires-Dist: ipython; extra == 'dev'
Requires-Dist: bumpversion; extra == 'dev'
Provides-Extra: docs
Requires-Dist: sphinx; extra == 'docs'
Requires-Dist: sphinx-rtd-theme; extra == 'docs'
Provides-Extra: testing
Requires-Dist: pytest; extra == 'testing'
Requires-Dist: pytest-cov; extra == 'testing'
Requires-Dist: pytest-html; extra == 'testing'
Requires-Dist: requests; extra == 'testing'
Requires-Dist: requests-mock; extra == 'testing'
